README.md
pyproject.toml
setup.cfg
setup.py
fitelio_ms_client.egg-info/PKG-INFO
fitelio_ms_client.egg-info/SOURCES.txt
fitelio_ms_client.egg-info/dependency_links.txt
fitelio_ms_client.egg-info/requires.txt
fitelio_ms_client.egg-info/top_level.txt
fms/__init__.py
fms/client.py
fms/settings.py
fms/pb/__init__.py
fms/pb/fms_pb2.py
fms/pb/fms_pb2_grpc.py