Metadata-Version: 2.1
Name: fitelio-ms-client
Version: 0.1.12
Summary: Messaging service client.
Home-page: https://gitlab.com/fitelio/messaging-service/client
Author: Vyacheslav Onufrienko
Author-email: onufrienkovi@gmail.com
License: UNKNOWN
Platform: UNKNOWN
Classifier: Environment :: Web Environment
Classifier: Intended Audience :: Developers
Classifier: Operating System :: OS Independent
Classifier: Programming Language :: Python
Classifier: Programming Language :: Python :: 3.7
Classifier: Programming Language :: Python :: 3.8
Classifier: Topic :: Internet :: WWW/HTTP
Classifier: Topic :: Software Development :: Libraries :: Python Modules
Requires-Python: >=3.7
Provides-Extra: test
Provides-Extra: lint
Provides-Extra: dev
